odoo/addons/dms_storage/README.rst
odoo/addons/dms_storage/__init__.py
odoo/addons/dms_storage/__manifest__.py
odoo/addons/dms_storage/i18n/dms_storage.pot
odoo/addons/dms_storage/i18n/it.po
odoo/addons/dms_storage/models/__init__.py
odoo/addons/dms_storage/models/dms_file.py
odoo/addons/dms_storage/models/dms_storage.py
odoo/addons/dms_storage/readme/CONTRIBUTORS.md
odoo/addons/dms_storage/readme/DESCRIPTION.md
odoo/addons/dms_storage/static/description/icon.png
odoo/addons/dms_storage/static/description/index.html
odoo/addons/dms_storage/tests/__init__.py
odoo/addons/dms_storage/tests/test_storage.py
odoo/addons/dms_storage/views/dms_storage.xml
odoo_addon_dms_storage-17.0.1.0.0.2.dist-info/METADATA
odoo_addon_dms_storage-17.0.1.0.0.2.dist-info/WHEEL
odoo_addon_dms_storage-17.0.1.0.0.2.dist-info/top_level.txt
odoo_addon_dms_storage-17.0.1.0.0.2.dist-info/RECORD
