Metadata-Version: 2.1
Name: odoo-addon-dms_storage
Version: 17.0.1.0.0.2
Requires-Python: >=3.10
Requires-Dist: odoo-addon-dms>=17.0dev,<17.1dev
Requires-Dist: odoo-addon-fs_storage>=17.0dev,<17.1dev
Requires-Dist: odoo>=17.0a,<17.1dev
Summary: Integrate DMS with external Storages
Home-page: https://github.com/OCA/dms
License: AGPL-3
Author: CreuBlanca,Odoo Community Association (OCA)
Author-email: support@odoo-community.org
Classifier: Programming Language :: Python
Classifier: Framework :: Odoo
Classifier: Framework :: Odoo :: 17.0
Classifier: License :: OSI Approved :: GNU Affero General Public License v3
